bdi_kit-0.9.0.dist-info/licenses/LICENSE.txt
bdikit/__init__.py
bdikit/api.py
bdikit/chatbot.py
bdikit/config.py
bdikit/download.py
bdikit/mapping_functions.py
bdikit/mcp_server.py
bdikit/utils.py
bdikit/matching_evaluation/__init__.py
bdikit/matching_evaluation/schema_matching.py
bdikit/matching_evaluation/value_matching.py
bdikit/resource/gdc_schema.json
bdikit/resource/synapse_schema.json
bdikit/schema_matching/__init__.py
bdikit/schema_matching/base.py
bdikit/schema_matching/llm.py
bdikit/schema_matching/magneto.py
bdikit/schema_matching/matcher_factory.py
bdikit/schema_matching/maxvalsim.py
bdikit/schema_matching/twophase.py
bdikit/schema_matching/valentine.py
bdikit/standards/__init__.py
bdikit/standards/base.py
bdikit/standards/dataframe.py
bdikit/standards/gdc.py
bdikit/standards/standard_factory.py
bdikit/standards/synapse.py
bdikit/value_matching/__init__.py
bdikit/value_matching/base.py
bdikit/value_matching/llm.py
bdikit/value_matching/llm_numeric.py
bdikit/value_matching/matcher_factory.py
bdikit/value_matching/polyfuzz.py
tests/__init__.py
tests/test_api.py
tests/test_mapping_functions.py
tests/test_matcher_factory.py
tests/test_schema_matching.py
tests/test_value_matching.py
bdi_kit-0.9.0.dist-info/METADATA
bdi_kit-0.9.0.dist-info/WHEEL
bdi_kit-0.9.0.dist-info/entry_points.txt
bdi_kit-0.9.0.dist-info/top_level.txt
bdi_kit-0.9.0.dist-info/RECORD
