Metadata-Version: 2.4
Name: bdi-kit
Version: 0.9.0
Summary: BDI-Kit Library
Home-page: https://github.com/VIDA-NYU/bdi-kit
Author: 
Author-email: 
Maintainer: 
Maintainer-email: 
License: Apache-2.0
Keywords: BDF,Data Harmonization,NYU
Classifier: Development Status :: 5 - Production/Stable
Classifier: Intended Audience :: Science/Research
Classifier: License :: OSI Approved :: Apache Software License
Classifier: Topic :: Scientific/Engineering
Requires-Python: >=3.9
License-File: LICENSE.txt
Requires-Dist: polyfuzz
Requires-Dist: gensim>=4.3.3
Requires-Dist: pandas
Requires-Dist: valentine>0.2.0
Requires-Dist: torch
Requires-Dist: transformers<4.57.0
Requires-Dist: tqdm
Requires-Dist: scikit-learn
Requires-Dist: flair[word-embeddings]>=0.14.0
Requires-Dist: requests
Requires-Dist: scipy
Requires-Dist: matplotlib<3.9
Requires-Dist: panel!=1.4.3
Requires-Dist: nltk>=3.9.1
Requires-Dist: magneto-python
Requires-Dist: json-repair
Requires-Dist: litellm
Provides-Extra: mcp
Requires-Dist: mcp[cli]; extra == "mcp"
Provides-Extra: chatbot
Requires-Dist: mcp[cli]; extra == "chatbot"
Requires-Dist: streamlit; extra == "chatbot"
Requires-Dist: langchain; extra == "chatbot"
Requires-Dist: langchain-litellm; extra == "chatbot"
Requires-Dist: langchain-mcp-adapters; extra == "chatbot"
Dynamic: classifier
Dynamic: description
Dynamic: description-content-type
Dynamic: home-page
Dynamic: keywords
Dynamic: license
Dynamic: license-file
Dynamic: provides-extra
Dynamic: requires-dist
Dynamic: requires-python
Dynamic: summary
